pyWikiCommons/__init__.py
pyWikiCommons/props.py
pyWikiCommons/pyWikiCommons.py
pyWikiCommons-0.0.5.dist-info/LICENSE
pyWikiCommons-0.0.5.dist-info/METADATA
pyWikiCommons-0.0.5.dist-info/WHEEL
pyWikiCommons-0.0.5.dist-info/top_level.txt
pyWikiCommons-0.0.5.dist-info/RECORD
